ustreasurycurve/__init__.py
ustreasurycurve/nominalRates.py
ustreasurycurve/realRates.py
ustreasurycurve-0.0.9.dist-info/licenses/LICENSE
ustreasurycurve-0.0.9.dist-info/METADATA
ustreasurycurve-0.0.9.dist-info/WHEEL
ustreasurycurve-0.0.9.dist-info/top_level.txt
ustreasurycurve-0.0.9.dist-info/RECORD
