Metadata-Version: 2.4
Name: ustreasurycurve
Version: 0.0.9
Summary: Pulls all available daily real and nominal yield curves from the US Treasury's website
Home-page: https://github.com/oisinkenny/ustreasurycurve
Author: Oisin Kenny
Author-email: oisinkenn@gmail.com
Classifier: Programming Language :: Python :: 3
Classifier: License :: OSI Approved :: MIT License
Classifier: Operating System :: OS Independent
Requires-Python: >=3.6
License-File: LICENSE
Dynamic: author
Dynamic: author-email
Dynamic: classifier
Dynamic: description
Dynamic: description-content-type
Dynamic: home-page
Dynamic: license-file
Dynamic: requires-python
Dynamic: summary
